uformer_pytorch/__init__.py
uformer_pytorch/uformer_pytorch.py
uformer_pytorch-0.0.8.dist-info/LICENSE
uformer_pytorch-0.0.8.dist-info/METADATA
uformer_pytorch-0.0.8.dist-info/WHEEL
uformer_pytorch-0.0.8.dist-info/top_level.txt
uformer_pytorch-0.0.8.dist-info/RECORD
